elyzo/__init__.py
elyzo/files.py
elyzo/requests.py
elyzo-0.1.25.dist-info/METADATA
elyzo-0.1.25.dist-info/WHEEL
elyzo-0.1.25.dist-info/top_level.txt
elyzo-0.1.25.dist-info/RECORD
