Metadata-Version: 2.4
Name: elyzo
Version: 0.1.25
Summary: A client library for making secure requests within the Elyzo runtime.
Home-page: https://github.com/adrianmm12/elyzo-core/elyzo-py
Author: Adrian Muniz
Author-email: adrian@elyzo.ai
License: MIT
Classifier: Development Status :: 4 - Beta
Classifier: Intended Audience :: Developers
Classifier: License :: OSI Approved :: MIT License
Classifier: Programming Language :: Python :: 3
Classifier: Operating System :: OS Independent
Classifier: Topic :: Software Development :: Libraries :: Python Modules
Requires-Python: >=3.7
Requires-Dist: requests
Dynamic: author
Dynamic: author-email
Dynamic: classifier
Dynamic: description
Dynamic: description-content-type
Dynamic: home-page
Dynamic: license
Dynamic: requires-dist
Dynamic: requires-python
Dynamic: summary
